README.rst
setup.py
src/fc_simesh_mayavi/__init__.py
src/fc_simesh_mayavi/demos.py
src/fc_simesh_mayavi/siMesh.py
src/fc_simesh_mayavi/siMeshElt.py
src/fc_simesh_mayavi/tools.py
src/fc_simesh_mayavi.egg-info/PKG-INFO
src/fc_simesh_mayavi.egg-info/SOURCES.txt
src/fc_simesh_mayavi.egg-info/dependency_links.txt
src/fc_simesh_mayavi.egg-info/requires.txt
src/fc_simesh_mayavi.egg-info/top_level.txt