Metadata-Version: 1.1
Name: fc-simesh-mayavi
Version: 0.0.2
Summary: Mayavi add-on to the fc_simesh package
Home-page: http://www.math.univ-paris13.fr/~cuvelier/software
Author: Francois Cuvelier
Author-email: cuvelier@math.univ-paris13.fr
License: BSD
Platform: Linux
Classifier: Topic :: Scientific/Engineering
